wormutils/Error_Handler.py
wormutils/__init__.py
wormutils/can_connect_to.py
wormutils/check_balance.py
wormutils/chemlabel.py
wormutils/convert.py
wormutils/find_HKF.py
wormutils/format_coeff.py
wormutils/format_equation.py
wormutils/get_colors.py
wormutils/import_package_resources.py
wormutils/isnotebook.py
wormutils/parse_formula_ox.py
wormutils-0.2.0.dist-info/licenses/LICENSE.txt
wormutils-0.2.0.dist-info/METADATA
wormutils-0.2.0.dist-info/WHEEL
wormutils-0.2.0.dist-info/top_level.txt
wormutils-0.2.0.dist-info/RECORD
